examples/__init__.py
examples/hello_world.py
kernel/__init__.py
kernel/channel.py
kernel/context.py
kernel/exceptions.py
kernel/functions.py
kernel/jobs.py
kernel/kernel.py
kernel/lifecycles.py
kernel/module.py
kernel/service.py
kernel/settings.py
kernel/states.py
test/__init__.py
test/bootstrap.py
test/test_kernel.py
mkernel-0.2.0.dist-info/LICENSE
mkernel-0.2.0.dist-info/METADATA
mkernel-0.2.0.dist-info/WHEEL
mkernel-0.2.0.dist-info/top_level.txt
mkernel-0.2.0.dist-info/zip-safe
mkernel-0.2.0.dist-info/RECORD
