Metadata-Version: 2.1
Name: mkernel
Version: 0.2.0
Summary: Kernel for extensible python program environment
Home-page: https://github.com/meerk40t/mkernel
Author: Tatarize
Author-email: tatarize@gmail.com
License: MIT
Keywords: kernel,console,timers,channels
Classifier: Development Status :: 5 - Production/Stable
Classifier: License :: OSI Approved :: MIT License
Classifier: Operating System :: OS Independent
Classifier: Programming Language :: Python
Classifier: Programming Language :: Python :: 3.6
Classifier: Programming Language :: Python :: 3.7
Classifier: Programming Language :: Python :: 3.8
Classifier: Programming Language :: Python :: 3.9
Classifier: Programming Language :: Python :: 3.10
Classifier: Topic :: Utilities
License-File: LICENSE
